spgdataset/__init__.py
spgdataset/audiofileindex.py
spgdataset/dataset.py
spgdataset/dataset_router.py
spgdataset/memcache.py
spgdataset/utils.py
spgdataset/assets/mel_filters.npz
spgdataset/audio/__init__.py
spgdataset/audio/utils.py
spgdataset-0.0.2.dist-info/LICENSE
spgdataset-0.0.2.dist-info/METADATA
spgdataset-0.0.2.dist-info/WHEEL
spgdataset-0.0.2.dist-info/top_level.txt
spgdataset-0.0.2.dist-info/RECORD
