Metadata-Version: 2.2
Name: spgdataset
Version: 0.0.2
Summary: SpectrogramDataset
Author-email: Sergey Skrebnev <sergey.skrebnev@gmail.com>
License: Copyright 2025 Sergey Skrebnev
Project-URL: Homepage, https://github.com/skrbnv/spgdataset
Classifier: Programming Language :: Python :: 3
Classifier: License :: OSI Approved :: MIT License
Classifier: Operating System :: OS Independent
Requires-Python: >=3.7
License-File: LICENSE
Requires-Dist: numpy>=1.21.0
Requires-Dist: soundfile>=0.10
Requires-Dist: torch>=2.1.0
Requires-Dist: tqdm
